cotton_iconify/__init__.py
cotton_iconify/cli.py
cotton_iconify/core.py
cotton_iconify/generators.py
cotton_iconify/utils.py
cotton_iconify-0.1.2.dist-info/METADATA
cotton_iconify-0.1.2.dist-info/WHEEL
cotton_iconify-0.1.2.dist-info/entry_points.txt
cotton_iconify-0.1.2.dist-info/licenses/LICENSE
cotton_iconify-0.1.2.dist-info/RECORD
