Metadata-Version: 2.4
Name: cotton-iconify
Version: 0.1.2
Summary: Generate iconify icons as django-cotton components.
Project-URL: Source, https://github.com/nklsw/cotton-iconify/
Project-URL: Bug Reports, https://github.com/nklsw/cotton-iconify/issues
Author: nklsw
License: MIT License
License-File: LICENSE
Requires-Python: <4,>=3.10
Requires-Dist: requests>=2.32.3
